render_engine/.gitignore
render_engine/__init__.py
render_engine/__main__.py
render_engine/_base_object.py
render_engine/archive.py
render_engine/blog.py
render_engine/collection.py
render_engine/engine.py
render_engine/feeds.py
render_engine/hookspecs.py
render_engine/links.py
render_engine/page.py
render_engine/plugins.py
render_engine/py.typed
render_engine/site.py
render_engine/site_map.py
render_engine/themes.py
render_engine/extras/__init__.py
render_engine/parsers/markdown.py
render_engine/render_engine_templates/__init__.py
render_engine/render_engine_templates/archive.html
render_engine/render_engine_templates/base.html
render_engine/render_engine_templates/base_collection_path.md
render_engine/render_engine_templates/page.html
render_engine/render_engine_templates/rss2.0.xml
render_engine/render_engine_templates/rss2.0_items.xml
render_engine/render_engine_templates/sitemap.xml
render_engine/render_engine_templates/sitemap_item.xml
render_engine/render_engine_templates/base_templates/_archive.html
render_engine/render_engine_templates/base_templates/_base.html
render_engine/render_engine_templates/base_templates/_page.html
render_engine/render_engine_templates/components/footer.html
render_engine/render_engine_templates/components/page_title.html
render_engine/utils/__init__.py
render_engine-2025.10.1.dist-info/METADATA
render_engine-2025.10.1.dist-info/WHEEL
render_engine-2025.10.1.dist-info/top_level.txt
render_engine-2025.10.1.dist-info/RECORD
