Metadata-Version: 2.4
Name: render_engine
Version: 2025.10.1
Summary: A Flexible Static Site Generator for Python
Project-URL: homepage, https://github.com/render-engine/render-engine/
Project-URL: repository, https://github.com/render-engine/render-engine/
Project-URL: documentation, https://render-engine.readthedocs.io/en/latest/
Requires-Python: >=3.10
Requires-Dist: jinja2
Requires-Dist: markdown2
Requires-Dist: more-itertools
Requires-Dist: pluggy
Requires-Dist: python-dateutil
Requires-Dist: python-frontmatter
Requires-Dist: python-slugify
Requires-Dist: render-engine-parser
Requires-Dist: render-engine-markdown
Requires-Dist: rich
Provides-Extra: cli
Requires-Dist: render-engine-cli; extra == "cli"
Provides-Extra: extras
Requires-Dist: render-engine-sitemap; extra == "extras"
Provides-Extra: dev
Requires-Dist: cookiecutter; extra == "dev"
Requires-Dist: ephemeral-port-reserve; extra == "dev"
Requires-Dist: httpx; extra == "dev"
Requires-Dist: mkdocs; extra == "dev"
Requires-Dist: mkdocs-material; extra == "dev"
Requires-Dist: mkdocstrings[python]; extra == "dev"
Requires-Dist: mypy; extra == "dev"
Requires-Dist: pre-commit; extra == "dev"
Requires-Dist: pymdown-extensions; extra == "dev"
Requires-Dist: pytest; extra == "dev"
Requires-Dist: pytest-cov; extra == "dev"
Requires-Dist: pytest-mock; extra == "dev"
Requires-Dist: ruff; extra == "dev"
Requires-Dist: toml; extra == "dev"
Requires-Dist: watchfiles; extra == "dev"
